odoo8_addon_purchase_rfq_number-8.0.1.0.0.99.dev12-py3.8-nspkg.pth
odoo_addons/purchase_rfq_number/README.rst
odoo_addons/purchase_rfq_number/__init__.py
odoo_addons/purchase_rfq_number/__openerp__.py
odoo_addons/purchase_rfq_number/data/data.xml
odoo_addons/purchase_rfq_number/i18n/de.po
odoo_addons/purchase_rfq_number/i18n/es.po
odoo_addons/purchase_rfq_number/i18n/fi.po
odoo_addons/purchase_rfq_number/i18n/fr.po
odoo_addons/purchase_rfq_number/i18n/fr_FR.po
odoo_addons/purchase_rfq_number/i18n/it.po
odoo_addons/purchase_rfq_number/i18n/nl.po
odoo_addons/purchase_rfq_number/i18n/pt_BR.po
odoo_addons/purchase_rfq_number/i18n/purchase_rfq_number.pot
odoo_addons/purchase_rfq_number/i18n/ro.po
odoo_addons/purchase_rfq_number/i18n/sl.po
odoo_addons/purchase_rfq_number/models/__init__.py
odoo_addons/purchase_rfq_number/models/purchase.py
odoo_addons/purchase_rfq_number/static/description/icon.png
odoo_addons/purchase_rfq_number/tests/__init__.py
odoo_addons/purchase_rfq_number/tests/test_rfq_number.py
odoo8_addon_purchase_rfq_number-8.0.1.0.0.99.dev12.dist-info/METADATA
odoo8_addon_purchase_rfq_number-8.0.1.0.0.99.dev12.dist-info/WHEEL
odoo8_addon_purchase_rfq_number-8.0.1.0.0.99.dev12.dist-info/namespace_packages.txt
odoo8_addon_purchase_rfq_number-8.0.1.0.0.99.dev12.dist-info/top_level.txt
odoo8_addon_purchase_rfq_number-8.0.1.0.0.99.dev12.dist-info/RECORD
